LICENSE.txt
README.rst
setup.py
lemoncheesecake_requests/__init__.py
lemoncheesecake_requests/__version__.py
lemoncheesecake_requests.egg-info/PKG-INFO
lemoncheesecake_requests.egg-info/SOURCES.txt
lemoncheesecake_requests.egg-info/dependency_links.txt
lemoncheesecake_requests.egg-info/requires.txt
lemoncheesecake_requests.egg-info/top_level.txt