Metadata-Version: 1.2
Name: lemoncheesecake-requests
Version: 0.3.0
Summary: Test Storytelling for requests
Home-page: https://lemoncheesecake-requests.readthedocs.io
Author: Nicolas Delon
Author-email: nicolas.delon@gmail.com
License: Apache License (Version 2.0)
Project-URL: Documentation, https://lemoncheesecake-requests.readthedocs.io.
Project-URL: Source, https://github.com/lemoncheesecake/lemoncheesecake-requests
Project-URL: Tracker, https://github.com/lemoncheesecake/lemoncheesecake-requests/issues
Keywords: QA testing lemoncheesecake requests
Platform: UNKNOWN
Classifier: Development Status :: 4 - Beta
Classifier: Environment :: Console
Classifier: Intended Audience :: Developers
Classifier: License :: OSI Approved :: Apache Software License
Classifier: Operating System :: MacOS
Classifier: Operating System :: Microsoft :: Windows
Classifier: Operating System :: POSIX
Classifier: Programming Language :: Python :: 3
Classifier: Programming Language :: Python :: 3.7
Classifier: Programming Language :: Python :: 3.8
Classifier: Programming Language :: Python :: 3.9
Classifier: Programming Language :: Python :: 3.10
Classifier: Programming Language :: Python :: 3 :: Only
Classifier: Topic :: Software Development :: Quality Assurance
Classifier: Topic :: Software Development :: Testing
Requires-Python: >=3.7
